manta/__init__.py
manta/__main__.py
manta/cli.py
manta/io_core.py
manta/manta.py
manta/memory_core.py
manta/utils.py
manta/ethernet/__init__.py
manta/ethernet/liteeth_gen.py
manta/ethernet/sink_bridge.py
manta/ethernet/source_bridge.py
manta/logic_analyzer/__init__.py
manta/logic_analyzer/capture.py
manta/logic_analyzer/fsm.py
manta/logic_analyzer/playback.py
manta/logic_analyzer/trigger_block.py
manta/uart/__init__.py
manta/uart/receive_bridge.py
manta/uart/receiver.py
manta/uart/transmit_bridge.py
manta/uart/transmitter.py
manta_fpga-1.1.0.dist-info/LICENSE.txt
manta_fpga-1.1.0.dist-info/METADATA
manta_fpga-1.1.0.dist-info/WHEEL
manta_fpga-1.1.0.dist-info/entry_points.txt
manta_fpga-1.1.0.dist-info/top_level.txt
manta_fpga-1.1.0.dist-info/RECORD
