Metadata-Version: 2.1
Name: manta-fpga
Version: 1.1.0
Summary: A configurable and approachable tool for FPGA debugging and rapid prototyping
Author-email: Fischer Moseley <fischer.moseley@gmail.com>
Project-URL: Homepage, https://github.com/fischermoseley/manta
Project-URL: Documentation, https://fischermoseley.github.io/manta
Project-URL: Issues, https://github.com/fischermoseley/manta/issues
Classifier: License :: OSI Approved :: GNU General Public License v3 (GPLv3)
Requires-Python: >=3.9
License-File: LICENSE.txt
Requires-Dist: amaranth[builtin-yosys]>=0.5.0
Requires-Dist: PyYAML
Requires-Dist: pyserial
Requires-Dist: liteeth==2023.12
Requires-Dist: pyvcd
Provides-Extra: dev
Requires-Dist: pytest; extra == "dev"
Requires-Dist: pytest-cov; extra == "dev"
Requires-Dist: codecov; extra == "dev"
Requires-Dist: pre-commit; extra == "dev"
Requires-Dist: ruff; extra == "dev"
Requires-Dist: mkdocs-material; extra == "dev"
Requires-Dist: mkdocstrings[python]; extra == "dev"
Requires-Dist: mike; extra == "dev"
